[
  {
    "type": "effect_on_condition",
    "id": "EOC_FORCE_LOCATION_CENTER",
    "eoc_type": "EVENT",
    "required_event": "game_start",
    "effect": [
      {
        "u_location_variable": { "context_val": "loc" },
        "target_params": { "om_special": "evac_center", "om_terrain": "evac_center_13", "search_range": 200, "z": 0 }
      },
      { "reveal_map": { "context_val": "loc" }, "radius": 2 }
    ]
  },
  {
    "type": "overmap_special",
    "id": "evac_center",
    "overmaps": [
      { "point": [ 0, 0, 0 ], "overmap": "refctr_fence_NW_north" },
      { "point": [ 1, 0, 0 ], "overmap": "refctr_fence_h_north" },
      { "point": [ 2, 0, 0 ], "overmap": "refctr_fence_h_north" },
      { "point": [ 3, 0, 0 ], "overmap": "refctr_fence_h_north" },
      { "point": [ 4, 0, 0 ], "overmap": "refctr_fence_h_north" },
      { "point": [ 0, 1, 0 ], "overmap": "refctr_fence_v_south" },
      { "point": [ 1, 1, 0 ], "overmap": "refctr_field" },
      { "point": [ 2, 1, 0 ], "overmap": "refctr_field" },
      { "point": [ 3, 1, 0 ], "overmap": "refctr_field" },
      { "point": [ 4, 1, 0 ], "overmap": "refctr_field" },
      { "point": [ 0, 2, 0 ], "overmap": "refctr_fence_v_south" },
      { "point": [ 1, 2, 0 ], "overmap": "refctr_field" },
      { "point": [ 2, 2, 0 ], "overmap": "refctr_field" },
      { "point": [ 3, 2, 0 ], "overmap": "refctr_field" },
      { "point": [ 4, 2, 0 ], "overmap": "refctr_field" },
      { "point": [ 0, 3, 0 ], "overmap": "refctr_fence_v_south" },
      { "point": [ 1, 3, 0 ], "overmap": "refctr_field" },
      { "point": [ 2, 3, 0 ], "overmap": "refctr_field" },
      { "point": [ 3, 3, 0 ], "overmap": "refctr_field" },
      { "point": [ 4, 3, 0 ], "overmap": "refctr_field" },
      { "point": [ 0, 4, 0 ], "overmap": "refctr_fence_v_south" },
      { "point": [ 1, 4, 0 ], "overmap": "refctr_field" },
      { "point": [ 2, 4, 0 ], "overmap": "refctr_field" },
      { "point": [ 3, 4, 0 ], "overmap": "refctr_field" },
      { "point": [ 4, 4, 0 ], "overmap": "refctr_field" },
      { "point": [ 5, 0, 0 ], "overmap": "refctr_fence_h_north" },
      { "point": [ 6, 0, 0 ], "overmap": "refctr_fence_h_north" },
      { "point": [ 7, 0, 0 ], "overmap": "refctr_fence_h_north" },
      { "point": [ 8, 0, 0 ], "overmap": "refctr_fence_h_north" },
      { "point": [ 9, 0, 0 ], "overmap": "refctr_fence_h_north" },
      { "point": [ 5, 1, 0 ], "overmap": "refctr_field" },
      { "point": [ 6, 1, 0 ], "overmap": "refctr_field" },
      { "point": [ 7, 1, 0 ], "overmap": "refctr_field" },
      { "point": [ 8, 1, 0 ], "overmap": "refctr_field" },
      { "point": [ 9, 1, 0 ], "overmap": "refctr_field" },
      { "point": [ 5, 2, 0 ], "overmap": "refctr_field" },
      { "point": [ 6, 2, 0 ], "overmap": "refctr_field" },
      { "point": [ 7, 2, 0 ], "overmap": "refctr_field" },
      { "point": [ 8, 2, 0 ], "overmap": "refctr_field" },
      { "point": [ 9, 2, 0 ], "overmap": "refctr_field" },
      { "point": [ 5, 3, 0 ], "overmap": "refctr_field" },
      { "point": [ 6, 3, 0 ], "overmap": "refctr_field" },
      { "point": [ 7, 3, 0 ], "overmap": "refctr_field" },
      { "point": [ 8, 3, 0 ], "overmap": "refctr_field" },
      { "point": [ 9, 3, 0 ], "overmap": "refctr_field" },
      { "point": [ 5, 4, 0 ], "overmap": "refctr_field" },
      { "point": [ 6, 4, 0 ], "overmap": "refctr_field" },
      { "point": [ 7, 4, 0 ], "overmap": "refctr_field" },
      { "point": [ 8, 4, 0 ], "overmap": "refctr_field" },
      { "point": [ 9, 4, 0 ], "overmap": "refctr_field" },
      { "point": [ 10, 0, 0 ], "overmap": "refctr_fence_h_north" },
      { "point": [ 11, 0, 0 ], "overmap": "refctr_fence_h_north" },
      { "point": [ 12, 0, 0 ], "overmap": "refctr_fence_h_north" },
      { "point": [ 13, 0, 0 ], "overmap": "refctr_fence_h_north" },
      { "point": [ 14, 0, 0 ], "overmap": "refctr_fence_NE_north" },
      { "point": [ 10, 1, 0 ], "overmap": "refctr_field" },
      { "point": [ 11, 1, 0 ], "overmap": "refctr_field" },
      { "point": [ 12, 1, 0 ], "overmap": "refctr_field" },
      { "point": [ 13, 1, 0 ], "overmap": "refctr_field" },
      { "point": [ 14, 1, 0 ], "overmap": "refctr_fence_v_north" },
      { "point": [ 10, 2, 0 ], "overmap": "refctr_field" },
      { "point": [ 11, 2, 0 ], "overmap": "refctr_field" },
      { "point": [ 12, 2, 0 ], "overmap": "refctr_field" },
      { "point": [ 13, 2, 0 ], "overmap": "refctr_field" },
      { "point": [ 14, 2, 0 ], "overmap": "refctr_fence_v_north" },
      { "point": [ 10, 3, 0 ], "overmap": "refctr_field" },
      { "point": [ 11, 3, 0 ], "overmap": "refctr_field" },
      { "point": [ 12, 3, 0 ], "overmap": "refctr_field" },
      { "point": [ 13, 3, 0 ], "overmap": "refctr_field" },
      { "point": [ 14, 3, 0 ], "overmap": "refctr_fence_v_north" },
      { "point": [ 10, 4, 0 ], "overmap": "refctr_field" },
      { "point": [ 11, 4, 0 ], "overmap": "refctr_field" },
      { "point": [ 12, 4, 0 ], "overmap": "refctr_field" },
      { "point": [ 13, 4, 0 ], "overmap": "refctr_field" },
      { "point": [ 14, 4, 0 ], "overmap": "refctr_fence_v_north" },
      { "point": [ 0, 5, 0 ], "overmap": "refctr_fence_v_south" },
      { "point": [ 1, 5, 0 ], "overmap": "refctr_field" },
      { "point": [ 2, 5, 0 ], "overmap": "refctr_field" },
      { "point": [ 3, 5, 0 ], "overmap": "refctr_field" },
      { "point": [ 4, 5, 0 ], "overmap": "refctr_field" },
      { "point": [ 0, 6, 0 ], "overmap": "refctr_fence_v_south" },
      { "point": [ 1, 6, 0 ], "overmap": "refctr_field" },
      { "point": [ 2, 6, 0 ], "overmap": "refctr_field" },
      { "point": [ 3, 6, 0 ], "overmap": "refctr_field" },
      { "point": [ 4, 6, 0 ], "overmap": "refctr_field" },
      { "point": [ 0, 7, 0 ], "overmap": "refctr_fence_v_south" },
      { "point": [ 1, 7, 0 ], "overmap": "refctr_field" },
      { "point": [ 2, 7, 0 ], "overmap": "refctr_field" },
      { "point": [ 3, 7, 0 ], "overmap": "refctr_field" },
      { "point": [ 4, 7, 0 ], "overmap": "refctr_field" },
      { "point": [ 0, 8, 0 ], "overmap": "refctr_fence_v_south" },
      { "point": [ 1, 8, 0 ], "overmap": "refctr_field" },
      { "point": [ 2, 8, 0 ], "overmap": "refctr_field" },
      { "point": [ 3, 8, 0 ], "overmap": "refctr_field" },
      { "point": [ 4, 8, 0 ], "overmap": "refctr_field" },
      { "point": [ 0, 9, 0 ], "overmap": "refctr_fence_v_south" },
      { "point": [ 1, 9, 0 ], "overmap": "refctr_field" },
      { "point": [ 2, 9, 0 ], "overmap": "refctr_field" },
      { "point": [ 3, 9, 0 ], "overmap": "refctr_field" },
      { "point": [ 4, 9, 0 ], "overmap": "refctr_field" },
      { "point": [ 5, 5, 0 ], "overmap": "evac_center_1_north" },
      { "point": [ 6, 5, 0 ], "overmap": "evac_center_2_north" },
      { "point": [ 7, 5, 0 ], "overmap": "evac_center_3_north" },
      { "point": [ 8, 5, 0 ], "overmap": "evac_center_4_north" },
      { "point": [ 9, 5, 0 ], "overmap": "evac_center_5_north" },
      { "point": [ 5, 6, 0 ], "overmap": "evac_center_6_north" },
      { "point": [ 6, 6, 0 ], "overmap": "evac_center_7_north" },
      { "point": [ 7, 6, 0 ], "overmap": "evac_center_8_north" },
      { "point": [ 8, 6, 0 ], "overmap": "evac_center_9_north" },
      { "point": [ 9, 6, 0 ], "overmap": "evac_center_10_north" },
      { "point": [ 5, 7, 0 ], "overmap": "evac_center_11_north" },
      { "point": [ 6, 7, 0 ], "overmap": "evac_center_12_north" },
      {
        "point": [ 7, 7, 0 ],
        "overmap": "evac_center_13_north",
        "camp": "free_merchants",
        "camp_name": "Refugee Center"
      },
      { "point": [ 8, 7, 0 ], "overmap": "evac_center_14_north" },
      { "point": [ 9, 7, 0 ], "overmap": "evac_center_15_north" },
      { "point": [ 5, 8, 0 ], "overmap": "evac_center_16_north" },
      { "point": [ 6, 8, 0 ], "overmap": "evac_center_17_north" },
      { "point": [ 7, 8, 0 ], "overmap": "evac_center_18_north" },
      { "point": [ 8, 8, 0 ], "overmap": "evac_center_19_north" },
      { "point": [ 9, 8, 0 ], "overmap": "evac_center_20_north" },
      { "point": [ 5, 9, 0 ], "overmap": "evac_center_21_north" },
      { "point": [ 6, 9, 0 ], "overmap": "evac_center_22_north" },
      { "point": [ 7, 9, 0 ], "overmap": "evac_center_23_north" },
      { "point": [ 8, 9, 0 ], "overmap": "evac_center_24_north" },
      { "point": [ 9, 9, 0 ], "overmap": "evac_center_25_north" },
      { "point": [ 10, 5, 0 ], "overmap": "refctr_field" },
      { "point": [ 11, 5, 0 ], "overmap": "refctr_field" },
      { "point": [ 12, 5, 0 ], "overmap": "refctr_field" },
      { "point": [ 13, 5, 0 ], "overmap": "refctr_field" },
      { "point": [ 14, 5, 0 ], "overmap": "refctr_fence_v_north" },
      { "point": [ 10, 6, 0 ], "overmap": "refctr_field" },
      { "point": [ 11, 6, 0 ], "overmap": "refctr_field" },
      { "point": [ 12, 6, 0 ], "overmap": "refctr_field" },
      { "point": [ 13, 6, 0 ], "overmap": "refctr_field" },
      { "point": [ 14, 6, 0 ], "overmap": "refctr_fence_v_north" },
      { "point": [ 10, 7, 0 ], "overmap": "refctr_field" },
      { "point": [ 11, 7, 0 ], "overmap": "refctr_field" },
      { "point": [ 12, 7, 0 ], "overmap": "refctr_field" },
      { "point": [ 13, 7, 0 ], "overmap": "refctr_field" },
      { "point": [ 14, 7, 0 ], "overmap": "refctr_fence_v_north" },
      { "point": [ 10, 8, 0 ], "overmap": "refctr_field" },
      { "point": [ 11, 8, 0 ], "overmap": "refctr_field" },
      { "point": [ 12, 8, 0 ], "overmap": "refctr_field" },
      { "point": [ 13, 8, 0 ], "overmap": "refctr_field" },
      { "point": [ 14, 8, 0 ], "overmap": "refctr_fence_v_north" },
      { "point": [ 10, 9, 0 ], "overmap": "refctr_field" },
      { "point": [ 11, 9, 0 ], "overmap": "refctr_field" },
      { "point": [ 12, 9, 0 ], "overmap": "refctr_field" },
      { "point": [ 13, 9, 0 ], "overmap": "refctr_field" },
      { "point": [ 14, 9, 0 ], "overmap": "refctr_fence_v_north" },
      { "point": [ 0, 10, 0 ], "overmap": "refctr_fence_v_south" },
      { "point": [ 1, 10, 0 ], "overmap": "refctr_field" },
      { "point": [ 2, 10, 0 ], "overmap": "refctr_field" },
      { "point": [ 3, 10, 0 ], "overmap": "refctr_field" },
      { "point": [ 4, 10, 0 ], "overmap": "refctr_field" },
      { "point": [ 0, 11, 0 ], "overmap": "refctr_fence_v_south" },
      { "point": [ 1, 11, 0 ], "overmap": "refctr_field" },
      { "point": [ 2, 11, 0 ], "overmap": "refctr_field" },
      { "point": [ 3, 11, 0 ], "overmap": "refctr_field" },
      { "point": [ 4, 11, 0 ], "overmap": "refctr_field" },
      { "point": [ 0, 12, 0 ], "overmap": "refctr_fence_v_south" },
      { "point": [ 1, 12, 0 ], "overmap": "refctr_field" },
      { "point": [ 2, 12, 0 ], "overmap": "refctr_field" },
      { "point": [ 3, 12, 0 ], "overmap": "refctr_field" },
      { "point": [ 4, 12, 0 ], "overmap": "refctr_field" },
      { "point": [ 0, 13, 0 ], "overmap": "refctr_fence_v_south" },
      { "point": [ 1, 13, 0 ], "overmap": "refctr_field" },
      { "point": [ 2, 13, 0 ], "overmap": "refctr_field" },
      { "point": [ 3, 13, 0 ], "overmap": "refctr_field" },
      { "point": [ 4, 13, 0 ], "overmap": "refctr_field" },
      { "point": [ 0, 14, 0 ], "overmap": "refctr_fence_SW_north" },
      { "point": [ 1, 14, 0 ], "overmap": "refctr_fence_h_south" },
      { "point": [ 2, 14, 0 ], "overmap": "refctr_fence_h_south" },
      { "point": [ 3, 14, 0 ], "overmap": "refctr_fence_h_south" },
      { "point": [ 4, 14, 0 ], "overmap": "refctr_fence_h_south" },
      { "point": [ 5, 10, 0 ], "overmap": "refctr_field" },
      { "point": [ 6, 10, 0 ], "overmap": "refctr_field" },
      { "point": [ 7, 10, 0 ], "overmap": "refctr_road_north" },
      { "point": [ 8, 10, 0 ], "overmap": "refctr_field" },
      { "point": [ 9, 10, 0 ], "overmap": "refctr_field" },
      { "point": [ 5, 11, 0 ], "overmap": "refctr_field" },
      { "point": [ 6, 11, 0 ], "overmap": "refctr_field" },
      { "point": [ 7, 11, 0 ], "overmap": "refctr_road_north" },
      { "point": [ 8, 11, 0 ], "overmap": "refctr_field" },
      { "point": [ 9, 11, 0 ], "overmap": "refctr_field" },
      { "point": [ 5, 12, 0 ], "overmap": "refctr_field" },
      { "point": [ 6, 12, 0 ], "overmap": "refctr_field" },
      { "point": [ 7, 12, 0 ], "overmap": "refctr_road_north" },
      { "point": [ 8, 12, 0 ], "overmap": "refctr_field" },
      { "point": [ 9, 12, 0 ], "overmap": "refctr_field" },
      { "point": [ 5, 13, 0 ], "overmap": "refctr_field" },
      { "point": [ 6, 13, 0 ], "overmap": "refctr_field" },
      { "point": [ 7, 13, 0 ], "overmap": "refctr_road_north" },
      { "point": [ 8, 13, 0 ], "overmap": "refctr_field" },
      { "point": [ 9, 13, 0 ], "overmap": "refctr_field" },
      { "point": [ 5, 14, 0 ], "overmap": "refctr_fence_h_south" },
      { "point": [ 6, 14, 0 ], "overmap": "refctr_fence_entrance_L_north" },
      { "point": [ 7, 14, 0 ], "overmap": "refctr_S3e_north" },
      { "point": [ 8, 14, 0 ], "overmap": "refctr_fence_entrance_R_north" },
      { "point": [ 9, 14, 0 ], "overmap": "refctr_fence_h_south" },
      { "point": [ 10, 10, 0 ], "overmap": "refctr_field" },
      { "point": [ 11, 10, 0 ], "overmap": "refctr_field" },
      { "point": [ 12, 10, 0 ], "overmap": "refctr_field" },
      { "point": [ 13, 10, 0 ], "overmap": "refctr_field" },
      { "point": [ 14, 10, 0 ], "overmap": "refctr_fence_v_north" },
      { "point": [ 10, 11, 0 ], "overmap": "refctr_field" },
      { "point": [ 11, 11, 0 ], "overmap": "refctr_field" },
      { "point": [ 12, 11, 0 ], "overmap": "refctr_field" },
      { "point": [ 13, 11, 0 ], "overmap": "refctr_field" },
      { "point": [ 14, 11, 0 ], "overmap": "refctr_fence_v_north" },
      { "point": [ 10, 12, 0 ], "overmap": "refctr_field" },
      { "point": [ 11, 12, 0 ], "overmap": "refctr_field" },
      { "point": [ 12, 12, 0 ], "overmap": "refctr_field" },
      { "point": [ 13, 12, 0 ], "overmap": "refctr_field" },
      { "point": [ 14, 12, 0 ], "overmap": "refctr_fence_v_north" },
      { "point": [ 10, 13, 0 ], "overmap": "refctr_field" },
      { "point": [ 11, 13, 0 ], "overmap": "refctr_field" },
      { "point": [ 12, 13, 0 ], "overmap": "refctr_field" },
      { "point": [ 13, 13, 0 ], "overmap": "refctr_field" },
      { "point": [ 14, 13, 0 ], "overmap": "refctr_fence_v_north" },
      { "point": [ 10, 14, 0 ], "overmap": "refctr_fence_h_south" },
      { "point": [ 11, 14, 0 ], "overmap": "refctr_fence_h_south" },
      { "point": [ 12, 14, 0 ], "overmap": "refctr_fence_h_south" },
      { "point": [ 13, 14, 0 ], "overmap": "refctr_fence_h_south" },
      { "point": [ 14, 14, 0 ], "overmap": "refctr_fence_SE_north" },
      { "point": [ 6, 6, 1 ], "overmap": "evac_center_7_z1_north" },
      { "point": [ 7, 6, 1 ], "overmap": "evac_center_8_z1_north" },
      { "point": [ 8, 6, 1 ], "overmap": "evac_center_9_z1_north" },
      { "point": [ 6, 7, 1 ], "overmap": "evac_center_12_z1_north" },
      { "point": [ 7, 7, 1 ], "overmap": "evac_center_13_z1_north" },
      { "point": [ 8, 7, 1 ], "overmap": "evac_center_14_z1_north" },
      { "point": [ 6, 8, 1 ], "overmap": "evac_center_17_z1_north" },
      { "point": [ 7, 8, 1 ], "overmap": "evac_center_18_z1_north" },
      { "point": [ 8, 8, 1 ], "overmap": "evac_center_19_z1_north" },
      { "point": [ 6, 7, 2 ], "overmap": "evac_center_12_z2_north" },
      { "point": [ 7, 7, 2 ], "overmap": "evac_center_13_z2_north" },
      { "point": [ 8, 7, 2 ], "overmap": "evac_center_14_z2_north" },
      { "point": [ 4, 4, -1 ], "overmap": "special_earth" },
      { "point": [ 5, 4, -1 ], "overmap": "special_earth" },
      { "point": [ 6, 4, -1 ], "overmap": "special_earth" },
      { "point": [ 7, 4, -1 ], "overmap": "special_earth" },
      { "point": [ 8, 4, -1 ], "overmap": "special_earth" },
      { "point": [ 9, 4, -1 ], "overmap": "special_earth" },
      { "point": [ 10, 4, -1 ], "overmap": "special_earth" },
      { "point": [ 4, 5, -1 ], "overmap": "special_earth" },
      { "point": [ 5, 5, -1 ], "overmap": "special_earth" },
      { "point": [ 6, 5, -1 ], "overmap": "special_earth" },
      { "point": [ 7, 5, -1 ], "overmap": "special_earth" },
      { "point": [ 8, 5, -1 ], "overmap": "special_earth" },
      { "point": [ 9, 5, -1 ], "overmap": "special_earth" },
      { "point": [ 10, 5, -1 ], "overmap": "special_earth" },
      { "point": [ 4, 6, -1 ], "overmap": "special_earth" },
      { "point": [ 5, 6, -1 ], "overmap": "special_earth" },
      { "point": [ 6, 6, -1 ], "overmap": "special_earth" },
      { "point": [ 7, 6, -1 ], "overmap": "special_earth" },
      { "point": [ 8, 6, -1 ], "overmap": "special_earth" },
      { "point": [ 9, 6, -1 ], "overmap": "special_earth" },
      { "point": [ 10, 6, -1 ], "overmap": "special_earth" },
      { "point": [ 4, 7, -1 ], "overmap": "special_earth" },
      { "point": [ 5, 7, -1 ], "overmap": "special_earth" },
      { "point": [ 6, 7, -1 ], "overmap": "special_earth" },
      { "point": [ 7, 7, -1 ], "overmap": "special_earth" },
      { "point": [ 8, 7, -1 ], "overmap": "special_earth" },
      { "point": [ 9, 7, -1 ], "overmap": "special_earth" },
      { "point": [ 10, 7, -1 ], "overmap": "special_earth" },
      { "point": [ 4, 8, -1 ], "overmap": "special_earth" },
      { "point": [ 5, 8, -1 ], "overmap": "special_earth" },
      { "point": [ 6, 8, -1 ], "overmap": "special_earth" },
      { "point": [ 7, 8, -1 ], "overmap": "special_earth" },
      { "point": [ 8, 8, -1 ], "overmap": "special_earth" },
      { "point": [ 9, 8, -1 ], "overmap": "special_earth" },
      { "point": [ 10, 8, -1 ], "overmap": "special_earth" },
      { "point": [ 4, 9, -1 ], "overmap": "special_earth" },
      { "point": [ 5, 9, -1 ], "overmap": "special_earth" },
      { "point": [ 6, 9, -1 ], "overmap": "special_earth" },
      { "point": [ 7, 9, -1 ], "overmap": "special_earth" },
      { "point": [ 8, 9, -1 ], "overmap": "special_earth" },
      { "point": [ 9, 9, -1 ], "overmap": "special_earth" },
      { "point": [ 10, 9, -1 ], "overmap": "special_earth" },
      { "point": [ 4, 10, -1 ], "overmap": "special_earth" },
      { "point": [ 5, 10, -1 ], "overmap": "special_earth" },
      { "point": [ 6, 10, -1 ], "overmap": "special_earth" },
      { "point": [ 7, 10, -1 ], "overmap": "special_earth" },
      { "point": [ 8, 10, -1 ], "overmap": "special_earth" },
      { "point": [ 9, 10, -1 ], "overmap": "special_earth" },
      { "point": [ 10, 10, -1 ], "overmap": "special_earth" },
      { "point": [ 4, 4, -2 ], "overmap": "special_rock" },
      { "point": [ 5, 4, -2 ], "overmap": "special_rock" },
      { "point": [ 6, 4, -2 ], "overmap": "special_rock" },
      { "point": [ 7, 4, -2 ], "overmap": "special_rock" },
      { "point": [ 8, 4, -2 ], "overmap": "special_rock" },
      { "point": [ 9, 4, -2 ], "overmap": "special_rock" },
      { "point": [ 10, 4, -2 ], "overmap": "special_rock" },
      { "point": [ 4, 5, -2 ], "overmap": "special_rock" },
      { "point": [ 5, 5, -2 ], "overmap": "special_rock" },
      { "point": [ 6, 5, -2 ], "overmap": "special_rock" },
      { "point": [ 7, 5, -2 ], "overmap": "special_rock" },
      { "point": [ 8, 5, -2 ], "overmap": "special_rock" },
      { "point": [ 9, 5, -2 ], "overmap": "special_rock" },
      { "point": [ 10, 5, -2 ], "overmap": "special_rock" },
      { "point": [ 4, 6, -2 ], "overmap": "special_rock" },
      { "point": [ 5, 6, -2 ], "overmap": "special_rock" },
      { "point": [ 6, 6, -2 ], "overmap": "special_rock" },
      { "point": [ 7, 6, -2 ], "overmap": "special_rock" },
      { "point": [ 8, 6, -2 ], "overmap": "special_rock" },
      { "point": [ 9, 6, -2 ], "overmap": "special_rock" },
      { "point": [ 10, 6, -2 ], "overmap": "special_rock" },
      { "point": [ 4, 7, -2 ], "overmap": "special_rock" },
      { "point": [ 5, 7, -2 ], "overmap": "special_rock" },
      { "point": [ 6, 7, -2 ], "overmap": "special_rock" },
      { "point": [ 7, 7, -2 ], "overmap": "special_rock" },
      { "point": [ 8, 7, -2 ], "overmap": "special_rock" },
      { "point": [ 9, 7, -2 ], "overmap": "special_rock" },
      { "point": [ 10, 7, -2 ], "overmap": "special_rock" },
      { "point": [ 4, 8, -2 ], "overmap": "special_rock" },
      { "point": [ 5, 8, -2 ], "overmap": "special_rock" },
      { "point": [ 6, 8, -2 ], "overmap": "special_rock" },
      { "point": [ 7, 8, -2 ], "overmap": "special_rock" },
      { "point": [ 8, 8, -2 ], "overmap": "special_rock" },
      { "point": [ 9, 8, -2 ], "overmap": "special_rock" },
      { "point": [ 10, 8, -2 ], "overmap": "special_rock" },
      { "point": [ 4, 9, -2 ], "overmap": "special_rock" },
      { "point": [ 5, 9, -2 ], "overmap": "special_rock" },
      { "point": [ 6, 9, -2 ], "overmap": "special_rock" },
      { "point": [ 7, 9, -2 ], "overmap": "special_rock" },
      { "point": [ 8, 9, -2 ], "overmap": "special_rock" },
      { "point": [ 9, 9, -2 ], "overmap": "special_rock" },
      { "point": [ 10, 9, -2 ], "overmap": "special_rock" },
      { "point": [ 4, 10, -2 ], "overmap": "special_rock" },
      { "point": [ 5, 10, -2 ], "overmap": "special_rock" },
      { "point": [ 6, 10, -2 ], "overmap": "special_rock" },
      { "point": [ 7, 10, -2 ], "overmap": "special_rock" },
      { "point": [ 8, 10, -2 ], "overmap": "special_rock" },
      { "point": [ 9, 10, -2 ], "overmap": "special_rock" },
      { "point": [ 10, 10, -2 ], "overmap": "special_rock" },
      { "point": [ 4, 4, -3 ], "overmap": "special_rock" },
      { "point": [ 5, 4, -3 ], "overmap": "special_rock" },
      { "point": [ 6, 4, -3 ], "overmap": "special_rock" },
      { "point": [ 7, 4, -3 ], "overmap": "special_rock" },
      { "point": [ 8, 4, -3 ], "overmap": "special_rock" },
      { "point": [ 9, 4, -3 ], "overmap": "special_rock" },
      { "point": [ 10, 4, -3 ], "overmap": "special_rock" },
      { "point": [ 4, 5, -3 ], "overmap": "special_rock" },
      { "point": [ 5, 5, -3 ], "overmap": "special_rock" },
      { "point": [ 6, 5, -3 ], "overmap": "special_rock" },
      { "point": [ 7, 5, -3 ], "overmap": "special_rock" },
      { "point": [ 8, 5, -3 ], "overmap": "special_rock" },
      { "point": [ 9, 5, -3 ], "overmap": "special_rock" },
      { "point": [ 10, 5, -3 ], "overmap": "special_rock" },
      { "point": [ 4, 6, -3 ], "overmap": "special_rock" },
      { "point": [ 5, 6, -3 ], "overmap": "special_rock" },
      { "point": [ 6, 6, -3 ], "overmap": "special_rock" },
      { "point": [ 7, 6, -3 ], "overmap": "special_rock" },
      { "point": [ 8, 6, -3 ], "overmap": "special_rock" },
      { "point": [ 9, 6, -3 ], "overmap": "special_rock" },
      { "point": [ 10, 6, -3 ], "overmap": "special_rock" },
      { "point": [ 4, 7, -3 ], "overmap": "special_rock" },
      { "point": [ 5, 7, -3 ], "overmap": "special_rock" },
      { "point": [ 6, 7, -3 ], "overmap": "special_rock" },
      { "point": [ 7, 7, -3 ], "overmap": "special_rock" },
      { "point": [ 8, 7, -3 ], "overmap": "special_rock" },
      { "point": [ 9, 7, -3 ], "overmap": "special_rock" },
      { "point": [ 10, 7, -3 ], "overmap": "special_rock" },
      { "point": [ 4, 8, -3 ], "overmap": "special_rock" },
      { "point": [ 5, 8, -3 ], "overmap": "special_rock" },
      { "point": [ 6, 8, -3 ], "overmap": "special_rock" },
      { "point": [ 7, 8, -3 ], "overmap": "special_rock" },
      { "point": [ 8, 8, -3 ], "overmap": "special_rock" },
      { "point": [ 9, 8, -3 ], "overmap": "special_rock" },
      { "point": [ 10, 8, -3 ], "overmap": "special_rock" },
      { "point": [ 4, 9, -3 ], "overmap": "special_rock" },
      { "point": [ 5, 9, -3 ], "overmap": "special_rock" },
      { "point": [ 6, 9, -3 ], "overmap": "special_rock" },
      { "point": [ 7, 9, -3 ], "overmap": "special_rock" },
      { "point": [ 8, 9, -3 ], "overmap": "special_rock" },
      { "point": [ 9, 9, -3 ], "overmap": "special_rock" },
      { "point": [ 10, 9, -3 ], "overmap": "special_rock" },
      { "point": [ 4, 10, -3 ], "overmap": "special_rock" },
      { "point": [ 5, 10, -3 ], "overmap": "special_rock" },
      { "point": [ 6, 10, -3 ], "overmap": "special_rock" },
      { "point": [ 7, 10, -3 ], "overmap": "special_rock" },
      { "point": [ 8, 10, -3 ], "overmap": "special_rock" },
      { "point": [ 9, 10, -3 ], "overmap": "special_rock" },
      { "point": [ 10, 10, -3 ], "overmap": "special_rock" },
      { "point": [ 4, 4, -4 ], "overmap": "special_deep_rock" },
      { "point": [ 5, 4, -4 ], "overmap": "special_deep_rock" },
      { "point": [ 6, 4, -4 ], "overmap": "special_deep_rock" },
      { "point": [ 7, 4, -4 ], "overmap": "special_deep_rock" },
      { "point": [ 8, 4, -4 ], "overmap": "special_deep_rock" },
      { "point": [ 9, 4, -4 ], "overmap": "special_deep_rock" },
      { "point": [ 10, 4, -4 ], "overmap": "special_deep_rock" },
      { "point": [ 4, 5, -4 ], "overmap": "special_deep_rock" },
      { "point": [ 5, 5, -4 ], "overmap": "special_deep_rock" },
      { "point": [ 6, 5, -4 ], "overmap": "special_deep_rock" },
      { "point": [ 7, 5, -4 ], "overmap": "special_deep_rock" },
      { "point": [ 8, 5, -4 ], "overmap": "special_deep_rock" },
      { "point": [ 9, 5, -4 ], "overmap": "special_deep_rock" },
      { "point": [ 10, 5, -4 ], "overmap": "special_deep_rock" },
      { "point": [ 4, 6, -4 ], "overmap": "special_deep_rock" },
      { "point": [ 5, 6, -4 ], "overmap": "special_deep_rock" },
      { "point": [ 6, 6, -4 ], "overmap": "special_deep_rock" },
      { "point": [ 7, 6, -4 ], "overmap": "special_deep_rock" },
      { "point": [ 8, 6, -4 ], "overmap": "special_deep_rock" },
      { "point": [ 9, 6, -4 ], "overmap": "special_deep_rock" },
      { "point": [ 10, 6, -4 ], "overmap": "special_deep_rock" },
      { "point": [ 4, 7, -4 ], "overmap": "special_deep_rock" },
      { "point": [ 5, 7, -4 ], "overmap": "special_deep_rock" },
      { "point": [ 6, 7, -4 ], "overmap": "special_deep_rock" },
      { "point": [ 7, 7, -4 ], "overmap": "special_deep_rock" },
      { "point": [ 8, 7, -4 ], "overmap": "special_deep_rock" },
      { "point": [ 9, 7, -4 ], "overmap": "special_deep_rock" },
      { "point": [ 10, 7, -4 ], "overmap": "special_deep_rock" },
      { "point": [ 4, 8, -4 ], "overmap": "special_deep_rock" },
      { "point": [ 5, 8, -4 ], "overmap": "special_deep_rock" },
      { "point": [ 6, 8, -4 ], "overmap": "special_deep_rock" },
      { "point": [ 7, 8, -4 ], "overmap": "special_deep_rock" },
      { "point": [ 8, 8, -4 ], "overmap": "special_deep_rock" },
      { "point": [ 9, 8, -4 ], "overmap": "special_deep_rock" },
      { "point": [ 10, 8, -4 ], "overmap": "special_deep_rock" },
      { "point": [ 4, 9, -4 ], "overmap": "special_deep_rock" },
      { "point": [ 5, 9, -4 ], "overmap": "special_deep_rock" },
      { "point": [ 6, 9, -4 ], "overmap": "special_deep_rock" },
      { "point": [ 7, 9, -4 ], "overmap": "special_deep_rock" },
      { "point": [ 8, 9, -4 ], "overmap": "special_deep_rock" },
      { "point": [ 9, 9, -4 ], "overmap": "special_deep_rock" },
      { "point": [ 10, 9, -4 ], "overmap": "special_deep_rock" },
      { "point": [ 4, 10, -4 ], "overmap": "special_deep_rock" },
      { "point": [ 5, 10, -4 ], "overmap": "special_deep_rock" },
      { "point": [ 6, 10, -4 ], "overmap": "special_deep_rock" },
      { "point": [ 7, 10, -4 ], "overmap": "special_deep_rock" },
      { "point": [ 8, 10, -4 ], "overmap": "special_deep_rock" },
      { "point": [ 9, 10, -4 ], "overmap": "special_deep_rock" },
      { "point": [ 10, 10, -4 ], "overmap": "special_deep_rock" },
      { "point": [ 7, 15, 0 ], "locations": [ "land", "road" ] }
    ],
    "connections": [ { "point": [ 7, 15, 0 ], "terrain": "road", "connection": "local_road", "from": [ 7, 14, 0 ] } ],
    "locations": [ "wilderness" ],
    "city_distance": [ 3, -1 ],
    "city_sizes": [ 4, -1 ],
    "occurrences": [ 1, 1 ],
    "priority": 1,
    "flags": [ "GLOBALLY_UNIQUE", "SAFE_AT_WORLDGEN", "MAN_MADE" ]
  }
]
